setup.py
rd_celery_email.egg-info/PKG-INFO
rd_celery_email.egg-info/SOURCES.txt
rd_celery_email.egg-info/dependency_links.txt
rd_celery_email.egg-info/not-zip-safe
rd_celery_email.egg-info/top_level.txt
rdcelery_email/__init__.py
rdcelery_email/admin.py
rdcelery_email/backends.py
rdcelery_email/models.py
rdcelery_email/tasks.py
rdcelery_email/tests.py
rdcelery_email/views.py