Metadata-Version: 1.1
Name: rd-celery-email
Version: 0.1.6
Summary: rd-celery-email
Home-page: https://bitbucket.org/andychiang/dj-celery-email
Author: andychiang
Author-email: rdandy@gmail.com
License: BSD
Keywords: django,celery,email
Platform: UNKNOWN
Classifier: Programming Language :: Python
Classifier: Topic :: Software Development :: Libraries :: Python Modules
Classifier: Framework :: Django
Classifier: Environment :: Web Environment
